ppe/__init__.py
ppe/core.py
ppe_debug-1.1.0.dist-info/licenses/LICENSE
tests/__init__.py
tests/test_ppe.py
ppe_debug-1.1.0.dist-info/METADATA
ppe_debug-1.1.0.dist-info/WHEEL
ppe_debug-1.1.0.dist-info/top_level.txt
ppe_debug-1.1.0.dist-info/RECORD
